{
  "id": "7db68415-04a2-43da-ad24-f175491751e9",
  "prevId": "00000000-0000-0000-0000-000000000000",
  "version": "7",
  "dialect": "postgresql",
  "tables": {
    "public.profile": {
      "name": "profile",
      "schema": "",
      "columns": {
        "id": {
          "name": "id",
          "type": "uuid",
          "primaryKey": true,
          "notNull": true,
          "default": "gen_random_uuid()"
        },
        "full_name": {
          "name": "full_name",
          "type": "varchar(255)",
          "primaryKey": false,
          "notNull": true
        },
        "father_name": {
          "name": "father_name",
          "type": "varchar(255)",
          "primaryKey": false,
          "notNull": false
        },
        "mother_name": {
          "name": "mother_name",
          "type": "varchar(255)",
          "primaryKey": false,
          "notNull": false
        },
        "address": {
          "name": "address",
          "type": "varchar(255)",
          "primaryKey": false,
          "notNull": false
        },
        "upzila": {
          "name": "upzila",
          "type": "varchar(255)",
          "primaryKey": false,
          "notNull": false
        },
        "zila": {
          "name": "zila",
          "type": "varchar(255)",
          "primaryKey": false,
          "notNull": false
        },
        "user_id": {
          "name": "user_id",
          "type": "uuid",
          "primaryKey": false,
          "notNull": true
        },
        "created_at": {
          "name": "created_at",
          "type": "timestamp with time zone",
          "primaryKey": false,
          "notNull": false,
          "default": "now()"
        },
        "updated_at": {
          "name": "updated_at",
          "type": "timestamp with time zone",
          "primaryKey": false,
          "notNull": false,
          "default": "now()"
        }
      },
      "indexes": {},
      "foreignKeys": {
        "profile_user_id_users_id_fk": {
          "name": "profile_user_id_users_id_fk",
          "tableFrom": "profile",
          "tableTo": "users",
          "columnsFrom": [
            "user_id"
          ],
          "columnsTo": [
            "id"
          ],
          "onDelete": "no action",
          "onUpdate": "no action"
        }
      },
      "compositePrimaryKeys": {},
      "uniqueConstraints": {},
      "policies": {},
      "checkConstraints": {},
      "isRLSEnabled": false
    },
    "public.users": {
      "name": "users",
      "schema": "",
      "columns": {
        "id": {
          "name": "id",
          "type": "uuid",
          "primaryKey": true,
          "notNull": true,
          "default": "gen_random_uuid()"
        },
        "email": {
          "name": "email",
          "type": "varchar(255)",
          "primaryKey": false,
          "notNull": false
        },
        "blood": {
          "name": "blood",
          "type": "varchar(255)",
          "primaryKey": false,
          "notNull": true
        },
        "last_donation": {
          "name": "last_donation",
          "type": "timestamp with time zone",
          "primaryKey": false,
          "notNull": false
        },
        "status": {
          "name": "status",
          "type": "user_status",
          "typeSchema": "public",
          "primaryKey": false,
          "notNull": false,
          "default": "'progress'"
        },
        "created_at": {
          "name": "created_at",
          "type": "timestamp with time zone",
          "primaryKey": false,
          "notNull": false,
          "default": "now()"
        },
        "updated_at": {
          "name": "updated_at",
          "type": "timestamp with time zone",
          "primaryKey": false,
          "notNull": false,
          "default": "now()"
        },
        "deleted_at": {
          "name": "deleted_at",
          "type": "timestamp with time zone",
          "primaryKey": false,
          "notNull": false
        }
      },
      "indexes": {},
      "foreignKeys": {},
      "compositePrimaryKeys": {},
      "uniqueConstraints": {
        "users_email_unique": {
          "name": "users_email_unique",
          "nullsNotDistinct": false,
          "columns": [
            "email"
          ]
        }
      },
      "policies": {},
      "checkConstraints": {},
      "isRLSEnabled": false
    }
  },
  "enums": {
    "public.blood_type": {
      "name": "blood_type",
      "schema": "public",
      "values": [
        "A_POSITIVE",
        "A_NEGATIVE",
        "B_POSITIVE",
        "B_NEGATIVE",
        "AB_POSITIVE",
        "AB_NEGATIVE",
        "O_POSITIVE",
        "O_NEGATIVE"
      ]
    },
    "public.user_status": {
      "name": "user_status",
      "schema": "public",
      "values": [
        "progress",
        "hold",
        "suspended",
        "deleted"
      ]
    }
  },
  "schemas": {},
  "sequences": {},
  "roles": {},
  "policies": {},
  "views": {},
  "_meta": {
    "columns": {},
    "schemas": {},
    "tables": {}
  }
}